ctodd_python_lib_data_science-1.0.0.dist-info/LICENSE.txt
ctodd_python_lib_data_science-1.0.0.dist-info/METADATA
ctodd_python_lib_data_science-1.0.0.dist-info/RECORD
ctodd_python_lib_data_science-1.0.0.dist-info/WHEEL
ctodd_python_lib_data_science-1.0.0.dist-info/top_level.txt
data_science_helpers/__init__.py
data_science_helpers/data_engineering_helpers.py
data_science_helpers/data_exploration_helpers.py
data_science_helpers/model_persistence_helpers.py
data_science_helpers/model_training_helpers.py
data_science_helpers/tests/__init__.py
data_science_helpers/tests/test_data_engineering_helpers.py
data_science_helpers/tests/test_data_exploration_helpers.py
data_science_helpers/tests/test_model_persistence_helpers.py
data_science_helpers/tests/test_model_training_helpers.py
