Metadata-Version: 2.1
Name: ctodd-python-lib-data-science
Version: 1.0.0
Summary: Python utilities used for practicing data science and engineering
Home-page: https://github.com/ChristopherHaydenTodd/ctodd-python-lib-data-science
Author: Christopher H. Todd
Author-email: Christopher.Hayden.Todd@gmail.com
License: MIT
Keywords: python,libraries,numpy,pandas,data science
Platform: UNKNOWN
Classifier: Development Status :: 5 - Production/Stable
Classifier: Intended Audience :: Developers
Classifier: Natural Language :: English
Classifier: Programming Language :: Python
Classifier: Programming Language :: Python :: 3
Classifier: Programming Language :: Python :: 3.6
Classifier: Programming Language :: Python :: 3.7
Classifier: Programming Language :: Python :: 3.8
Requires-Python: >3.6
Requires-Dist: pandas (>=0.24.2)
Requires-Dist: great-expectations (>=0.4.5)
Requires-Dist: tensorflow (>=1.13.1)
